sphinx_genai/__init__.py
sphinx_genai-0.0.5.dist-info/METADATA
sphinx_genai-0.0.5.dist-info/WHEEL
sphinx_genai-0.0.5.dist-info/RECORD
