Metadata-Version: 2.4
Name: sphinx-genai
Version: 0.0.5
Summary: TODO
Project-URL: Homepage, https://github.com/kaycebasques/sphinx-genai
Project-URL: Issues, https://github.com/kaycebasques/sphinx-genai/issues
Author-email: Kayce Basques <kaycebasques@gmail.com>
License-Expression: Apache-2.0
Classifier: Operating System :: OS Independent
Classifier: Programming Language :: Python :: 3
Requires-Python: >=3.8
Requires-Dist: nltk
Requires-Dist: sphinx
